photomaker/__init__.py
photomaker/res.py
photomaker-1.0.1.dist-info/LICENSE
photomaker-1.0.1.dist-info/METADATA
photomaker-1.0.1.dist-info/WHEEL
photomaker-1.0.1.dist-info/top_level.txt
photomaker-1.0.1.dist-info/RECORD
